LICENSE
MANIFEST.in
README.rst
setup.cfg
setup.py
sphinx_julia_theme/__init__.py
sphinx_julia_theme.egg-info/PKG-INFO
sphinx_julia_theme.egg-info/SOURCES.txt
sphinx_julia_theme.egg-info/dependency_links.txt
sphinx_julia_theme.egg-info/not-zip-safe
sphinx_julia_theme.egg-info/top_level.txt
sphinx_julia_theme/sphinx_julia_theme/layout.html
sphinx_julia_theme/sphinx_julia_theme/theme.conf
sphinx_julia_theme/sphinx_julia_theme/versions.html
sphinx_julia_theme/sphinx_julia_theme/static/julia.css_t