Metadata-Version: 1.1
Name: sphinx-julia-theme
Version: 0.0.2
Summary: Julia theme for Sphinx based on ReadTheDocs theme.
Home-page: https://github.com/syarra/sphinx_julia_theme/
Author: Sylvain Arreckx
Author-email: sylvain.arreckx@gmail.com
License: MIT
Platform: UNKNOWN
Classifier: Development Status :: 3 - Alpha
Classifier: Environment :: Console
Classifier: Environment :: Web Environment
Classifier: Intended Audience :: Developers
Classifier: Programming Language :: Python :: 2.7
Classifier: Programming Language :: Python :: 3
Classifier: Operating System :: OS Independent
Classifier: Topic :: Documentation
Classifier: Topic :: Software Development :: Documentation
